setup.py
pyhectane/__init__.py
pyhectane/connection.py
pyhectane/django.py
pyhectane.egg-info/PKG-INFO
pyhectane.egg-info/SOURCES.txt
pyhectane.egg-info/dependency_links.txt
pyhectane.egg-info/requires.txt
pyhectane.egg-info/top_level.txt