Metadata-Version: 1.1
Name: pyhectane
Version: 0.3.1
Summary: Python module for sending emails with Hectane
Home-page: https://github.com/hectane/python-hectane
Author: Nathan Osman
Author-email: nathan@quickmediasolutions.com
License: MIT
Platform: UNKNOWN
Classifier: Development Status :: 5 - Production/Stable
Classifier: Intended Audience :: Developers
Classifier: License :: OSI Approved :: MIT License
Classifier: Operating System :: OS Independent
Classifier: Programming Language :: Python
Classifier: Programming Language :: Python :: 2
Classifier: Programming Language :: Python :: 3
Classifier: Topic :: Software Development :: Libraries :: Python Modules
